docspace/__init__.py
docspace-0.0.1a0.dist-info/METADATA
docspace-0.0.1a0.dist-info/WHEEL
docspace-0.0.1a0.dist-info/licenses/LICENSE.txt
docspace-0.0.1a0.dist-info/RECORD
