Metadata-Version: 2.4
Name: docspace
Version: 0.0.1a0
Project-URL: Documentation, https://github.com/ysenarath/docspace#readme
Project-URL: Issues, https://github.com/ysenarath/docspace/issues
Project-URL: Source, https://github.com/ysenarath/docspace
Author-email: Yasas Senarath <12231659+ysenarath@users.noreply.github.com>
License-Expression: MIT
License-File: LICENSE.txt
Classifier: Development Status :: 4 - Beta
Classifier: Programming Language :: Python
Classifier: Programming Language :: Python :: 3.9
Classifier: Programming Language :: Python :: 3.10
Classifier: Programming Language :: Python :: 3.11
Classifier: Programming Language :: Python :: 3.12
Classifier: Programming Language :: Python :: Implementation :: CPython
Classifier: Programming Language :: Python :: Implementation :: PyPy
Requires-Python: >=3.9
